url_text_module/__init__.py
url_text_module/_version.py
url_text_module/classes.py
url_text_module/classification.py
url_text_module/clustering.py
url_text_module/constants.py
url_text_module/dimensionality_reduction.py
url_text_module/eda_utils.py
url_text_module/metric_utils.py
url_text_module/misc_utils.py
url_text_module/plotting_utils.py
url_text_module/preprocessing_utils.py
url_text_module/vectorizer_utils.py
url_text_module-0.6.1.dist-info/LICENSE
url_text_module-0.6.1.dist-info/METADATA
url_text_module-0.6.1.dist-info/WHEEL
url_text_module-0.6.1.dist-info/top_level.txt
url_text_module-0.6.1.dist-info/RECORD
