Metadata-Version: 2.1
Name: url-text-module
Version: 0.6.1
Summary: Text Module of REACT
Home-page: https://gitlab.com/react76/url-text-module
Author: Urban Risk Lab
Author-email: url_googleai@mit.edu
License: UNKNOWN
Project-URL: Bug Tracker, https://gitlab.com/react76/url-text-module/-/issues
Platform: UNKNOWN
Classifier: Programming Language :: Python :: 3
Classifier: License :: OSI Approved :: Apache Software License
Classifier: Operating System :: OS Independent
Requires-Python: >=3.7
License-File: LICENSE
Requires-Dist: aiohttp (==3.8.1)
Requires-Dist: aiosignal (==1.2.0)
Requires-Dist: async-timeout (==4.0.2)
Requires-Dist: asynctest (==0.13.0)
Requires-Dist: attrs (==21.4.0)
Requires-Dist: bleach (==4.1.0)
Requires-Dist: certifi (==2022.5.18.1)
Requires-Dist: chardet (==3.0.4)
Requires-Dist: charset-normalizer (==2.0.12)
Requires-Dist: click (==8.1.3)
Requires-Dist: colorama (==0.4.4)
Requires-Dist: cycler (==0.11.0)
Requires-Dist: datasets (==1.18.4)
Requires-Dist: dill (==0.3.5.1)
Requires-Dist: docutils (==0.18.1)
Requires-Dist: filelock (==3.7.1)
Requires-Dist: fonttools (==4.34.4)
Requires-Dist: frozenlist (==1.3.0)
Requires-Dist: fsspec (==2022.5.0)
Requires-Dist: fugashi (==1.1.2)
Requires-Dist: huggingface-hub (==0.8.1)
Requires-Dist: idna (==3.3)
Requires-Dist: importlib-metadata (==4.8.3)
Requires-Dist: ipadic (==1.0.0)
Requires-Dist: joblib (==1.1.0)
Requires-Dist: keyring (==23.4.1)
Requires-Dist: kiwisolver (==1.3.1)
Requires-Dist: matplotlib (==3.3.4)
Requires-Dist: multidict (==6.0.2)
Requires-Dist: multiprocess (==0.70.13)
Requires-Dist: nltk (==3.7)
Requires-Dist: numpy (==1.19.5)
Requires-Dist: packaging (==21.3)
Requires-Dist: pandas (==1.3.5)
Requires-Dist: Pillow (==8.4.0)
Requires-Dist: pkginfo (==1.8.3)
Requires-Dist: pyarrow (==8.0.0)
Requires-Dist: Pygments (==2.12.0)
Requires-Dist: pyparsing (==3.0.7)
Requires-Dist: python-dateutil (==2.8.2)
Requires-Dist: pytz (==2022.1)
Requires-Dist: PyYAML (==6.0)
Requires-Dist: readme-renderer (==34.0)
Requires-Dist: regex (==2022.7.9)
Requires-Dist: requests (==2.27.1)
Requires-Dist: requests-toolbelt (==0.9.1)
Requires-Dist: responses (==0.18.0)
Requires-Dist: rfc3986 (==1.5.0)
Requires-Dist: sacremoses (==0.0.53)
Requires-Dist: scikit-learn (==1.0.2)
Requires-Dist: scikit-learn-extra (==0.2.0)
Requires-Dist: scipy (==1.5.4)
Requires-Dist: seaborn (==0.11.2)
Requires-Dist: six (==1.16.0)
Requires-Dist: threadpoolctl (==3.1.0)
Requires-Dist: tokenizers (==0.12.1)
Requires-Dist: torch (==1.9.0)
Requires-Dist: tqdm (==4.64.0)
Requires-Dist: transformers (==4.17.0)
Requires-Dist: twine (==3.8.0)
Requires-Dist: typing-extensions (==4.1.1)
Requires-Dist: unidic-lite (==1.0.8)
Requires-Dist: urllib3 (==1.26.9)
Requires-Dist: webencodings (==0.5.1)
Requires-Dist: xxhash (==3.0.0)
Requires-Dist: yarl (==1.7.2)
Requires-Dist: zipp (==3.6.0)
